rabbit_youtube/__init__.py
rabbit_youtube/app_config.py
rabbit_youtube/youtube_utils.py
rabbit_youtube-0.1.1.data/scripts/rabbit-youtube.py
rabbit_youtube-0.1.1.dist-info/DESCRIPTION.rst
rabbit_youtube-0.1.1.dist-info/METADATA
rabbit_youtube-0.1.1.dist-info/RECORD
rabbit_youtube-0.1.1.dist-info/WHEEL
rabbit_youtube-0.1.1.dist-info/metadata.json
rabbit_youtube-0.1.1.dist-info/top_level.txt
