Metadata-Version: 2.0
Name: rabbit-youtube
Version: 0.1.1
Summary: rabbit youtube utils
Home-page: http://rabbitsrc.com/youtube
Author: Guoliang Li
Author-email: dev@liguoliang.com
License: Apache Software License
Platform: UNKNOWN
Requires-Dist: pytube
